{
  "title": "AWS EKS Setup",
  "description": "A Killercoda scenario to install AWS CLI & eksctl, configure AWS, and assume a role.",
  "difficulty": "beginner",
  "details": {
    "intro": {
      "text": "intro.md"
    },
    "steps": [
      { "title": "Install AWS CLI & eksctl", "text": "steps/step1.md" },
      { "title": "Set Up AWS Environment", "text": "steps/step2.md" },
      { "title": "Verify AWS Connectivity", "text": "steps/step3.md" },
      { "title": "Assume an IAM Role", "text": "steps/step4.md" },
      { "title": "Use Temporary Credentials", "text": "steps/step5.md" }
    ],
    "finish": {
      "text": "finish.md"
    }
  },
  "backend": {
    "imageid": "ubuntu"
  }
}


